setup.py
rajesh_test_pypi/__init__.py
rajesh_test_pypi/rajesh_test_pypi.py
rajesh_test_pypi.egg-info/PKG-INFO
rajesh_test_pypi.egg-info/SOURCES.txt
rajesh_test_pypi.egg-info/dependency_links.txt
rajesh_test_pypi.egg-info/top_level.txt