Metadata-Version: 2.1
Name: rajesh-test-pypi
Version: 1.1
Summary: A demo PyPI package
Author: Rajesh
Author-email: rajeshroy402@gmail.com
